dist/ka_com-2023.2.2.tar.gz
ka_com/__init__.py
ka_com/__version__.py
ka_com/com.py
ka_com/ioc.py
ka_com/pacmod.py
ka_com/py.typed
ka_com/data/__init__.py
ka_com/data/log.main.tenant.yml
ka_com/data/log.yml
ka_com-2023.2.2.dist-info/LICENSE.txt
ka_com-2023.2.2.dist-info/METADATA
ka_com-2023.2.2.dist-info/WHEEL
ka_com-2023.2.2.dist-info/top_level.txt
ka_com-2023.2.2.dist-info/RECORD
